README.md
setup.py
SpecLab_PyQt5/__init__.py
SpecLab_PyQt5.egg-info/PKG-INFO
SpecLab_PyQt5.egg-info/SOURCES.txt
SpecLab_PyQt5.egg-info/dependency_links.txt
SpecLab_PyQt5.egg-info/requires.txt
SpecLab_PyQt5.egg-info/top_level.txt
SpecLab_PyQt5/aux/__init__.py
SpecLab_PyQt5/aux/pyqtgraph_modifications.tar.gz
SpecLab_PyQt5/aux/param_files/__init__.py
SpecLab_PyQt5/aux/param_files/imXam_param.dat
SpecLab_PyQt5/aux/param_files/imXam_param.default.dat
SpecLab_PyQt5/aux/param_files/imXam_param_ARCES.dat
SpecLab_PyQt5/cfg/SpecLab_config.py
SpecLab_PyQt5/cfg/epar_imXam.py
SpecLab_PyQt5/doc/CHANGELOG.txt
SpecLab_PyQt5/doc/KNOWN_ISSUES.txt
SpecLab_PyQt5/doc/LICENSE.txt
SpecLab_PyQt5/doc/README.md
SpecLab_PyQt5/doc/__init__.py
SpecLab_PyQt5/gen/SpecLabFunctions.py
SpecLab_PyQt5/gen/__init__.py
SpecLab_PyQt5/gen/globals.py
SpecLab_PyQt5/gen/myfunc.py
SpecLab_PyQt5/imXam/__init__.py
SpecLab_PyQt5/imXam/imXam.py