Metadata-Version: 2.1
Name: SpecLab-PyQt5
Version: 1.0.0
Summary: A Python alternative for SAO/DS9+IRAF/imexam
Home-page: http://pypi.python.org/pypi/SpecLab/
Author: A. F. Kowalski
Author-email: adam.f.kowalski@colorado.edu
